setup.py
CacheAlchemy/__init__.py
CacheAlchemy/base_backend.py
CacheAlchemy/cached.py
CacheAlchemy/redis_backend.py
CacheAlchemy.egg-info/PKG-INFO
CacheAlchemy.egg-info/SOURCES.txt
CacheAlchemy.egg-info/dependency_links.txt
CacheAlchemy.egg-info/not-zip-safe
CacheAlchemy.egg-info/requires.txt
CacheAlchemy.egg-info/top_level.txt