Metadata-Version: 1.0
Name: CacheAlchemy
Version: 0.0.4
Summary: Cache SqlAlchemy entity to memory cache system
Home-page: https://github.com/ipconfiger/CacheAlchemy
Author: Alexander.Li
Author-email: superpowerlee@gmail.com
License: MIT License
Platform: UNKNOWN
